{
    "DATE": " 4-MAR-1987 12:32:08.30",
    "TOPICS": [
        "sugar"
    ],
    "PLACES": [
        "uk",
        "india"
    ],
    "NEWID": "1598",
    "TEXT": {
        "TITLE": "INDIA BUYS UP TO 10 CARGOES SUGAR - TRADERS",
        "DATELINE": "    LONDON, March 4 - ",
        "BODY": "India bought up to 10 cargoes of white\nsugar at a buying tender today which originally called for just\ntwo to three cargoes of March/April shipment, traders said.\n    London trader E D and F Man said it sold two cargoes at 233\ndlrs a tonne CIF for March/April shipment with an option to\nsell an additional two cargoes at the same price.\n    Traders said at least one other international trader made a\nsimilar contract while a French house sold two cargoes at an\noutright price of 233 dlrs CIF without the option. This brought\ntotal Indian purchases to at least six cargoes with traders\nhaving options to sell another four.\n Reuter\n\u0003"
    },
    "ORGS": [
        "ec",
        "gatt"
    ],
    "EXCHENGES": [
        "amex"
    ]
}