{
    "DATE": "20-OCT-1987 10:40:51.17",
    "TOPICS": [
        "grain",
        "wheat"
    ],
    "PLACES": [
        "usa",
        "sri-lanka"
    ],
    "NEWID": "20258",
    "TEXT": {
        "TITLE": "SRI LANKA POSTPONES EEP WHEAT TENDER - TRADE",
        "DATELINE": "    KANSAS CITY, Oct 20 - ",
        "BODY": "Sri Lanka has postponed until\nNovember its tender for 75,000 tonnes of wheat under the export\nbonus program, originally scheduled for today, U.S. exporters\nsaid.\n Reuter\n\u0003"
    },
    "ORGS": [
        "ec"
    ],
    "PEOPLE": [
        "lyng"
    ],
    "EXCHENGES": [
        "comex"
    ]
}