{
    "DATE": "29-JUN-1987 13:44:12.55",
    "TOPICS": [
        "acq"
    ],
    "ORGS": [
        "ec"
    ],
    "NEWID": "19780",
    "TEXT": {
        "TITLE": "CAROLCO PICTURES <CRC>, ORBIS IN AGREEMENT",
        "DATELINE": "    LOS ANGELES, June 29 - ",
        "BODY": "Carolco Pictures Inc said it signed\na letter of intent to exchange 2.2 mln of its shares for all\nOrbis Communications Inc stock within the next 60 days.\n    It said the Carolco shares used in the exchange are valued\nat 7.00 dlrs a share or a total value of 15.4 mln dlrs and will\nbe adjusted based on the price of Carolco shares on the closing\ndate.\n    It said Orbis management will remain in place for at least\nthree years.\n Reuter\n\u0003"
    },
    "PLACES": [
        "usa"
    ],
    "PEOPLE": [
        "reagan"
    ],
    "EXCHENGES": [
        "nasdaq"
    ]
}