{
    "DATE": "19-MAR-1987 14:38:06.02",
    "TOPICS": [
        "acq"
    ],
    "PLACES": [
        "usa"
    ],
    "NEWID": "7337",
    "TEXT": {
        "TITLE": "GREAT <GAMI> TO BUY STANDARD<SRD> UNITS' ASSETS",
        "DATELINE": "    CHICAGO, March 19 - ",
        "BODY": "Great American Management and\nInvestment Inc said its 80 pct-owned subsidiary agreed to buy\ncertain assets of two subsidiaries of Standard Oil Co, for 40\nmln dlrs and the assumption of certain liabilities.\n    Great American Industrial Group Inc agreed to acquire all\nthe U.S. and United Kingdom assets of Pfaudler Co and the stock\nof certain Brazilian, Mexican, and West German subsidiaries of\nKennecott Mining Corp, it said. Pfaudler and Kennecott are\nsubsidiaries of Standard Oil.\n Reuter\n\u0003"
    },
    "PEOPLE": [
        "herrington"
    ],
    "ORGS": [
        "ec"
    ],
    "EXCHENGES": [
        "biffex"
    ]
}