{
    "DATE": "29-JUN-1987 13:18:08.98",
    "TOPICS": [
        "acq"
    ],
    "ORGS": [
        "ec"
    ],
    "NEWID": "19767",
    "TEXT": {
        "TITLE": "UNIVERSAL COMMUNICATION <UCS> TO SELL ASSETS",
        "DATELINE": "    ROANOKE, Va., June 29 - ",
        "BODY": "Universal Communication Systems Inc\nsaid it has tentatively agreed to sell substantially all its\nassets for about 79 mln dlrs in cash and notes plus limited\nprofit participation.\n    The company said the terms of the sale have been approved\nby its board and by Prime Motor Inns Inc <PDQ>, owner of about\n84 pct of Universal's outstanding stock.\n    It described the purchaser as a subsidiary of a company in\nthe communications field which is one of the 100 largest U.S.\ncorporations.\n    The company said the transaction involves the payment of 20\nmln dlrs in cash, a non-interest bearing payment of 11.3 mln\ndlrs in four equal instalments over four years and two\npromissory notes guaranteed by an affiliate of the purchaser.\n    It said a 31.5 mln dlr 14 pct note is payable in four equal\ninstalments over four years. It said a 16.3 mln dlr 8.5 pct\nnote due Dec 31, 1992, includes participation in the 1992\nprofits of the acquiring company. Universdal said the profit\nelement can be terminated with payments by the purchaser of\neither five mln dlrs in 1988, six mln dlrs in 1989, seven mln\ndlrs in 1990 or eight mln dlrs in 1991.\n Reuter\n\u0003"
    },
    "PLACES": [
        "usa"
    ],
    "PEOPLE": [
        "reagan"
    ],
    "EXCHENGES": [
        "nasdaq"
    ]
}