{
    "DATE": "19-JUN-1987 11:17:39.53",
    "TOPICS": [
        "grain",
        "wheat"
    ],
    "ORGS": [
        "ec"
    ],
    "NEWID": "19213",
    "TEXT": {
        "TITLE": "TUNISIA BUYS 150,000 TONNES FRENCH WHEAT",
        "DATELINE": "    ****PARIS, June 19 - ",
        "BODY": "Tunisia has bought 150,000 tonnes of\nFrench soft wheat for August to December shipment at 76.70 dlrs\nper tonne fob with COFACE export credit, trade sources said.\n    This is the second French soft wheat export sale for the\n1987/88 season which starts on July 1 and follows a Brazilian\npurchase of 150,000 tonnes.\n    France sold around 300,000 tonnes of soft wheat to Tunisia\nduring the 1986/87 season.\n Reuter\n\u0003"
    },
    "PLACES": [
        "france"
    ],
    "PEOPLE": [
        "leigh-pemberton"
    ]
}