{
    "DATE": " 2-JUN-1987 11:42:19.36",
    "TOPICS": [
        "acq"
    ],
    "PLACES": [
        "usa"
    ],
    "PEOPLE": [
        "lawson"
    ],
    "NEWID": "18079",
    "TEXT": {
        "TITLE": "RAYCOMM TRANSWORLD <RACM.O> TO MAKE ACQUISITION",
        "DATELINE": "    FREEHOLD, N.J., June 2 - ",
        "BODY": "Raycomm Transworld Industries Inc\nsaid it has agreed in principle subject to board approvals to\nacquire Spiridellis Consulting Group Inc, a privately-held\ncomputer services consulting firm, for a number of common\nshares to be determined based on pretax earnings of Spiridellis\nover a five-year period.\n    The company said it will gaurantee that almost all of the\nissued shares will attain price levels ranging from five to\nnine dlrs each for two years after their issuance.\n    It said Spiridellis had revenues of 3,500,000 dlrs in\ncalendar 1986.\n Reuter\n\u0003"
    },
    "ORGS": [
        "icco"
    ]
}