{
    "DATE": "25-MAR-1987 09:11:08.30",
    "TOPICS": [
        "money-fx",
        "interest"
    ],
    "PLACES": [
        "uk"
    ],
    "NEWID": "9261",
    "TEXT": {
        "TITLE": "U.K. MONEY MARKET SURPLUS REVISED TO 250 MLN STG",
        "DATELINE": "    LONDON, March 25 - ",
        "BODY": "The Bank of England said it revised up\nits forecast of today's surplus in the money markets to 250 mln\nstg from its earlier estimate of a 150 mln.\n    The central bank has not operated in the market today.\n REUTER\n\u0003"
    },
    "PEOPLE": [
        "sumita"
    ],
    "ORGS": [
        "ec"
    ]
}