{
    "DATE": "30-MAR-1987 12:36:10.69",
    "TOPICS": [
        "earn"
    ],
    "PLACES": [
        "usa"
    ],
    "NEWID": "10907",
    "TEXT": {
        "TITLE": "GENERAL PUBLIC UTILITIES CORP <GPU> TWO MTHS NET",
        "DATELINE": "    PARSIPPANY, N.J., March 30 -\n    ",
        "BODY": "Shr 97 cts vs 81 cts\n    Net 60.8 mln vs 51.1 mln\n    Revs 487.4 mln vs 529.7 mln\n    12 mths\n    Shr 3.42 dlrs vs 2.18 dlrs\n    Net 215.0 mln vs 137.2 mln\n    Revs 2.74 billion vs 2.88 billion\n    NOTE: 1986 results restated for change in accounting.\n Reuter\n\u0003"
    },
    "PEOPLE": [
        "nakasone"
    ],
    "EXCHENGES": [
        "lme"
    ],
    "ORGS": [
        "ec"
    ]
}