{
    "DATE": "13-APR-1987 13:19:38.07",
    "TOPICS": [
        "trade"
    ],
    "NEWID": "16505",
    "TEXT": {
        "TITLE": "U.S. FEBRUARY TRADE TO BE REPORTED ON NEW BASIS",
        "DATELINE": "    WASHINGTON, April 13 - ",
        "BODY": "The February monthly merchandise\ntrade figures to be reported Tuesday by the Commerce Department\nwill be on a new basis reflecting more recent data, so avoiding\nfuture revisions of the monthly figure, Commerce officials\nsaid.\n    The overall January deficit of 14.8 billion dlrs will be\nrevised, but the February figure will be a final one, officials\nsaid.\n    Previously, the initial monthly figure has had to be\nrevised in subsequent months because of the time lag between\nthe report and the compiling of final estimates on imports and\nexports.\n    The reporting of the February trade data was delayed\nseveral weeks to permit gathering latest figures on imports and\nexports to give a clearer picture of the monthly trade balance.\n Reuter\n\u0003"
    },
    "PLACES": [
        "usa"
    ],
    "PEOPLE": [
        "rubio"
    ],
    "ORGS": [
        "ec"
    ],
    "EXCHENGES": [
        "lme"
    ]
}