{
    "DATE": "23-MAR-1987 10:26:33.25",
    "TOPICS": [
        "earn"
    ],
    "PLACES": [
        "usa"
    ],
    "NEWID": "8276",
    "TEXT": {
        "TITLE": "CITIZENS GROWTH <CITGS> OMITS QUARTERLY DIVIDEND",
        "DATELINE": "    JACKSON, Miss., March 20 - ",
        "BODY": "Citizens Growth Properties said\nit ommitted its regular quartelry dividend as a result of\ndecreased earnings, principally attributable to the default by\na borrower of the trust's laargest mortgage loan.\n    The trust last paid 12 cts on January 28.\n    The trust said it also reaffirmed a limited share\nrepurchase program subject to available cash flow in light of\nthe defaulted mortgage.               \n Reuter\n\u0003"
    },
    "EXCHENGES": [
        "cme"
    ],
    "ORGS": [
        "gatt"
    ],
    "PEOPLE": [
        "yeutter"
    ]
}