{
    "DATE": "19-OCT-1987 11:30:57.50",
    "TOPICS": [
        "acq"
    ],
    "PLACES": [
        "usa"
    ],
    "NEWID": "21319",
    "TEXT": {
        "TITLE": "INDUSTRIAL EQUITY HAS 5.4 PCT OF TRITON <OIL>",
        "DATELINE": "    WASHINGTON, Oct 19 - ",
        "BODY": "A group of firms led by Hong\nKong-based Industrial Equity (Pacific) Ltd, said it acquired\n969,515 shares of Triton Oil Corp common stock, or 5.4 pct of\nthe company's common stock outstanding.\n    Industrial Equity (Pacific), which is controlled by\nBrierley Investments Ltd <BRYW.WE> and which has applied with\nU.S. antitrust regulators to buy up to 50 pct of Triton's\ncommon stock, said the current 5.4 pct stake was acquired for\ninvestment purposes.\n    The company said it informed Triton of its present \"good\nfaith intention\" to buy more than 15 mln dlrs worth of Triton\nstock.\n    It said it also told Triton it \"may depending on market\nconditions acquire 50 pct or more and possibly 100 pct of the\nvoting securities of (Triton).\"\n    It said it received clearance to buy up to 50 pct of the\nstock on September 11.\n    Industrial Equity (Pacific) reported it bought 250,000\nshares of Triton common stock on October 8 at 22.50 dlrs a\nshare.\n Reuter\n\u0003"
    },
    "PEOPLE": [
        "stoltenberg",
        "james-baker"
    ],
    "ORGS": [
        "opec"
    ],
    "EXCHENGES": [
        "amex"
    ]
}