{
    "DATE": " 3-APR-1987 08:42:31.67",
    "TOPICS": [
        "acq"
    ],
    "PLACES": [
        "usa"
    ],
    "NEWID": "12822",
    "TEXT": {
        "TITLE": "ALTEX <AII> SETS ACQUISITION OF COMPUTER FIRMS",
        "DATELINE": "    DENVER, April 3 - ",
        "BODY": "Altex Industries Inc said it has agreed\nin principle to buy 82 pct of two privately-held affiliated\ncomputer retail companies for an undisclosed amount.\n    Altex said the Denver-based companies had revenues of over\nseven mln dlrs last year. They are Integrated Management Data\nSystems Inc, which sells accounting software systems to the oil\nand gas industry, and Integrated Management Systems Micro\nDistribution Division Inc, which distributes micro-computer\nproducts.\n    Altex said it expects to close the transaction, which is\nsubject to financing, in July.\n Reuter\n\u0003"
    },
    "ORGS": [
        "ec"
    ],
    "PEOPLE": [
        "eyskens"
    ],
    "EXCHENGES": [
        "nymex"
    ]
}