{
    "DATE": " 9-APR-1987 07:33:57.54",
    "TOPICS": [
        "earn"
    ],
    "PLACES": [
        "netherlands"
    ],
    "NEWID": "15438",
    "TEXT": {
        "TITLE": "NATNED FORECASTS 1987 RESULTS IN LINE WITH 1986",
        "DATELINE": "    THE HAGUE, April 9 - ",
        "BODY": "The Netherlands' largest insurer\nNationale Nederlanden NV <NTTN.AS> (NatNed) said it expected at\nleast unchanged results in 1987 after reporting 1986 net\nprofits up 5.3 pct to 635.5 mln guilders from 603.4 mln in\n1985,\n    Revenues increased by 0.5 pct to 17.35 billion guilders\nafter 17.27 billion the previous year, and the dividend was\nraised to 2.50 guilders per share from 2.38 guilders in 1985,\ncorrected on a capital increase.\n    The company said guilder revenue and profit were pressured\nby falls in exchange rates, particularly in the US and\nAustralian dollar and sterling.\n    Without these currency fluctuations, net profit would have\nbeen 30.7 mln guilders higher and revenue 1.97 billion higher,\nNatNed said.\n    The international share in turnover was 50 pct in 1986\ncompared with 52 pct in 1985.\n    The company's life insurance result fell to 365.7 mln\nguilders after 428.4 mln in 1985 due to currency influences,\ntighter interest margins and increased investment.\n    Claim payouts fell to 9.9 mln guilders after 66.6 mln the\nprevious year.\n    The company's total assets reached 69.87 billion guilders\nin 1986 against 67 billion the year before.\n    Assets per share equalled 65.68 guilders against 65.53.\n    Without these currency fluctuations, net profit would have\nbeen 30.7 mln guilders higher and revenue 1.97 billion higher,\nNatNed said.\n    The international share in turnover was 50 pct in 1986\ncompared with 52 pct in 1985.\n    The company's life insurance result fell to 365.7 mln\nguilders aft\n INTERRUPTED\n\u0003"
    },
    "ORGS": [
        "ec"
    ],
    "PEOPLE": [
        "miyazawa"
    ],
    "EXCHENGES": [
        "lme"
    ]
}