{
    "DATE": "19-JUN-1987 17:07:20.27",
    "TOPICS": [
        "acq"
    ],
    "ORGS": [
        "opec"
    ],
    "NEWID": "19451",
    "TEXT": {
        "TITLE": "GROUP UPS STAKE IN TANDY BRANDS <TAB> TO 6.9 PCT",
        "DATELINE": "    WASHINGTON, June 19 - ",
        "BODY": "A group of companies including\nChicago-based Coronet Insurance Co and Sunstates Corp, a\nJacksonville., Fla., real estate firm, said it raised its stake\nin Tandy Brands Inc to 175,900 shares, or 6.9 pct of the total.\n    In a filing with the Securities and Exchange Commission,\nthe group said it bought 43,600 Tandy common shares between May\n21 and June 9 for 633,333 dlrs in addition to the 132,300\nshares, or 5.2 pct, it had held previously.\n Reuter\n\u0003"
    },
    "PLACES": [
        "usa"
    ],
    "PEOPLE": [
        "yeutter"
    ],
    "EXCHENGES": [
        "nymex"
    ]
}