{
    "DATE": "23-APR-1987 19:08:09.42",
    "TOPICS": [
        "earn"
    ],
    "PLACES": [
        "usa"
    ],
    "PEOPLE": [
        "reagan"
    ],
    "NEWID": "17037",
    "TEXT": {
        "TITLE": "RORER GROUP INC <ROR> 1ST QTR NET",
        "DATELINE": "    FORT WASHINGTON, Pa., April 23 - \n    ",
        "BODY": "Oper shr profit 34 cts vs loss 78 cts\n    Oper net profit 7,434,000 vs loss 17.0 mln\n    Revs 201.2 mln vs 171.7 mln\n    Note: Year-ago oper exludes gain on sale of businesses of\n139.6 mln.\n    Year-ago oper includes charges of 27.8 mln resulting from\nallocation of the purchase price of Revlon's businesses to\ninventory and 7.1 mln for restructuring costs.\n Reuter\n\u0003"
    }
}