{
    "DATE": "29-JUN-1987 15:32:31.84",
    "TOPICS": [
        "acq"
    ],
    "ORGS": [
        "opec"
    ],
    "NEWID": "19860",
    "TEXT": {
        "TITLE": "KRAFT <KRA> COMPLETES FROSTEX ACQUISITION",
        "DATELINE": "    GLENVIEW, Ill., June 29 - ",
        "BODY": "Kraft Inc said it completed the\nacquisition of Frostex Foods Inc for undisclosed terms.\n    Kraft said last month it had signed a letter of intent to\nacquire the Austin, Texas-based foodservice distributor.\n Reuter\n\u0003"
    },
    "PLACES": [
        "usa"
    ],
    "PEOPLE": [
        "dauster"
    ],
    "EXCHENGES": [
        "nasdaq"
    ]
}