{
    "DATE": "26-MAR-1987 13:00:46.83",
    "TOPICS": [
        "acq"
    ],
    "PLACES": [
        "usa"
    ],
    "NEWID": "10042",
    "TEXT": {
        "TITLE": "<MERIDIAN ENERGY>, CASTONE END LETTER OF INTENT",
        "DATELINE": "    CHICAGO, March 26 - ",
        "BODY": "<Meridian Energy Inc> and Castone\nDevelopment Corp, a privately-held company, jointly announced\nthat they have decided to terminate the letter of intent under\nwhich Meridian would have acquired Castone.\n Reuter\n\u0003"
    },
    "PEOPLE": [
        "thatcher"
    ],
    "EXCHENGES": [
        "nycsce"
    ],
    "ORGS": [
        "ec"
    ]
}