{
    "DATE": " 2-JUN-1987 11:19:50.44",
    "TOPICS": [
        "earn"
    ],
    "PLACES": [
        "usa"
    ],
    "PEOPLE": [
        "lawson"
    ],
    "NEWID": "18052",
    "TEXT": {
        "TITLE": "GULF AND WESTERN INC <GW> 2ND QTR APRIL 30 NET",
        "DATELINE": "    NEW YORK, June 2 -\n    ",
        "BODY": "Shr 86 cts vs 73 cts\n    Net 52.7 mln vs 45.7 mln\n    Revs 989.9 mln vs 863.9 mln\n    Six mths\n    Shr 1.97 dlrs vs 1.28 dlrs\n    Net 122 mln vs 79.9 mln\n    Revs 2.078 billion vs 1.726 billion\n Reuter\n\u0003"
    },
    "ORGS": [
        "icco"
    ]
}