{
    "DATE": "24-APR-1987 13:07:35.68",
    "TOPICS": [
        "money-fx",
        "dlr",
        "yen"
    ],
    "PLACES": [
        "usa"
    ],
    "PEOPLE": [
        "james-baker"
    ],
    "NEWID": "17138",
    "TEXT": {
        "TITLE": "TREASURY'S BAKER - G-7 OPPOSE FURTHER DLR DROP",
        "DATELINE": "    WASHINGTON, April 24 - ",
        "BODY": "Treasury Secretary James Baker said\nthe Group of Seven countries, in seeking to foster stability in\nexchange markets, believe a further decline in the value of the\ndollar would be counterproductive.\n     In answer to questions by a business group, Baker said\nthat for one thing further reductions could make it\neconomically difficult for the surplus countries to grow,\nthereby making it difficult for them to purchase overseas\ngoods. In addition, Baker said he was opposed to the U.S.\nselling a yen denominated bond arguing that such a move might\nsend the wrong signal to markets.\n Reuter\n\u0003"
    },
    "ORGS": [
        "ec"
    ]
}