{
    "DATE": " 9-APR-1987 13:20:30.37",
    "TOPICS": [
        "earn"
    ],
    "PLACES": [
        "canada"
    ],
    "NEWID": "15769",
    "TEXT": {
        "TITLE": "<SULPETRO LTD> 1ST QTR JAN 31 LOSS",
        "DATELINE": "    CALGARY, Alberta, April 9 -\n    ",
        "BODY": "Shr not given\n    Net loss 9,900,000 vs loss 17,300,000\n    Revs 14.7 mln vs 29.8 mln\n    Note: Previous loss restated.\n Reuter\n\u0003"
    },
    "ORGS": [
        "ec"
    ],
    "PEOPLE": [
        "balladur"
    ],
    "EXCHENGES": [
        "nyce"
    ]
}