{
    "DATE": " 2-APR-1987 10:30:54.44",
    "TOPICS": [
        "earn"
    ],
    "PLACES": [
        "usa"
    ],
    "NEWID": "12579",
    "TEXT": {
        "TITLE": "AMERICAN REALTY <ARB> SETS RECORD DATE FOR OFFER",
        "DATELINE": "    DALLAS, April 2 - ",
        "BODY": "American Realty Trust said its board has\nset April 3 as the record date for its previously announced\nrights offering, and the rights will be issued on April 6 and\nexpire May 22.\n    Shareholders will be able to subscribe for 1.25 shares for\neach share held, at a price of 3.75 dlrs per share.\n Reuter\n\u0003"
    },
    "ORGS": [
        "ec"
    ],
    "PEOPLE": [
        "yeutter"
    ],
    "EXCHENGES": [
        "lme"
    ]
}