{
    "DATE": " 2-APR-1987 09:31:17.21",
    "TOPICS": [
        "earn"
    ],
    "PLACES": [
        "usa"
    ],
    "NEWID": "12531",
    "TEXT": {
        "TITLE": "SAN DIEGO GAS <SDO> SEES DECISION HURTING NET",
        "DATELINE": "    SAN DIEGO, April 2 - ",
        "BODY": "San Diego Gas and Electric Co said a\nCalifornia Public Utilities Commission decision to reconsider\nallowing only 20 mln dlrs of the 69 mln dlrs in San Onofre\nnuclear station costs it disallowed makes it likely that\nearnings in 1987 will be reduced at least 36 cts per share.\n    The company said if the decision to disallow the other 20\nmln dlrs is not changed, earnings would be penalized by another\n19 cts.\n Reuter\n\u0003"
    },
    "ORGS": [
        "ec"
    ],
    "PEOPLE": [
        "lawson"
    ],
    "EXCHENGES": [
        "lme"
    ]
}