{
    "DATE": " 6-MAR-1987 11:36:23.26",
    "TOPICS": [
        "acq"
    ],
    "PLACES": [
        "usa"
    ],
    "NEWID": "2672",
    "TEXT": {
        "TITLE": "DONALDSON <DCI> TO BUY MINE SAFETY <MNES> UNIT",
        "DATELINE": "    MINNEAPOLIS, March 6 - ",
        "BODY": "Donaldson Co Inc said it reached an\nagreement to buy the assets of the Filter Products Division of\nMine safety Appliances Co for undisclosed terms.\n    It said Filter Products will operate as part of Donaldson's\nIndustrial Group and its manufacturing operations will be\nrelocated to Dixon, Ill., from Evans City, Pa.\n    Donaldson said the acquisition complements its\nmicrofiltration business and internal research and development\nefforts.\n Reuter\n\u0003"
    },
    "PEOPLE": [
        "james-baker"
    ],
    "ORGS": [
        "ico-coffee"
    ],
    "EXCHENGES": [
        "amex"
    ]
}