{
    "DATE": "27-MAR-1987 06:22:35.40\u0005\u0005\u0005C G",
    "TOPICS": [
        "grain",
        "corn"
    ],
    "PLACES": [
        "south-africa"
    ],
    "NEWID": "10339",
    "TEXT": {
        "TITLE": "SOUTH AFRICAN MAIZE ESTIMATE CALLED CONSERVATIVE",
        "DATELINE": "   JOHANNESBURG, March 27 - ",
        "BODY": "The South African government's\nmaize production estimate of 7.8 mln tonnes for the current\nyear is \"rather too conservative,\" leading grain and produce\nmerchants Kahn and Kahn Pty Ltd said.\n    The company, in a detailed report, estimated the harvest as\nhigh as 8.3 mln tonnes and said if this forecast is met the\nostensible surplus for export will be approximately 2.25 mln\ntonnes.\n    \"This paradoxically is creating a problem for the Maize\nBoard,\" Kahn and Kahn said.\n    It said the maize export price currently is depressed and\nthe board is \"probably confronted with the necessity to maintain\nor slightly increase the internal price of maize again...To\noffset the ostensible loss which must be faced\" on exporting\nsurplus amounts.\n REUTER\n\u0003"
    },
    "PEOPLE": [
        "reagan",
        "nakasone"
    ],
    "EXCHENGES": [
        "nycsce"
    ],
    "ORGS": [
        "ec"
    ]
}