{
    "DATE": " 3-APR-1987 12:16:19.71",
    "TOPICS": [
        "acq"
    ],
    "PLACES": [
        "usa"
    ],
    "NEWID": "12981",
    "TEXT": {
        "TITLE": "ALLIED-SIGNAL <ALD> TO SELL ELECTRONICS UNIT",
        "DATELINE": "    MORRIS TOWNSHIP, N.J., April 3 - ",
        "BODY": "Allied-Signal Inc said it\nagreed to sell its Amphenol Products unit to a subsidiary of\nLPL Investments Group <LPLI>, a Wallingford, Conn., investment\ncompany, for 430 mln dlrs cash.\n    Closing is expected soon, pending appropriate approvals,\nthe company said. LPL indicated that at closing, warrants will\nbe sold which, when exercised, will reduce its stake in the\nsubsidiary, Amphenol Acquisition Co, to 60 pct, the company\nsaid.\n    Lisle, Ill.-based Amphenol had 1986 sales of about 500 mln\ndlrs. It makes brand name interconnection products.\n    LPL also said Merrill Lynch and Co has committed to buy 175\nmln dlrs of subordinated and preferred debt in the new LPL\nunit, according to Allied-Signal. Canadian Imperial Bank of\nCommerce has committed up to 340 mln dlrs in senior debt\nfinancing, it said.\n    Allied-Signal said in December it was offering for sale\nAmphenol and six other operating units in its electronics and\ninstrumentation sector.\n    Merrill Lynch, Needham and Co and Lazard Freres served as\nfinancial advisors, it said.\n Reuter\n\u0003"
    },
    "ORGS": [
        "ec"
    ],
    "PEOPLE": [
        "stoltenberg"
    ],
    "EXCHENGES": [
        "nyse",
        "nyce"
    ]
}