{
    "DATE": "20-MAR-1987 10:36:45.36",
    "TOPICS": [
        "acq"
    ],
    "PLACES": [
        "usa"
    ],
    "NEWID": "7704",
    "TEXT": {
        "TITLE": "ILLINOIS REGIONAL <ILLR> MULLS AFFILIATION",
        "DATELINE": "    ELMHURST, ILL., March 20 - ",
        "BODY": "Illinois Regional Bancorp said\nit is evaluating whether to affiliate with a larger bank\nholding company or continue to remain independent.\n    The 500 mln dlr-asset bank holding company said that in\nview of recent investor interest in suburban Chicago banks, it\nretained Merrill Lynch Capital markets to advise it on its\nalternatives.\n    Last year, Illinois Regional had discussions with\nMilwaukee-based Marine Corp <MCRP> but no agreement was\nreached, a company spokesman said.\n Reuter\n\u0003"
    },
    "PEOPLE": [
        "james-baker"
    ],
    "ORGS": [
        "ec"
    ],
    "EXCHENGES": [
        "simex"
    ]
}