{
    "DATE": "12-MAR-1987 12:36:05.30",
    "TOPICS": [
        "earn"
    ],
    "PLACES": [
        "usa"
    ],
    "NEWID": "4337",
    "TEXT": {
        "TITLE": "EQUITY OIL CO <EQTY> 4TH QTR LOSS",
        "DATELINE": "    SALT LAKE CITY, March 12 -\n    ",
        "BODY": "Shr loss nine cts vs profit 11 cts\n    Net loss 1,102,592 vs profit 1,364,763\n    Revs 2,836,508 vs 5,547,121\n    Year\n    Shr loss six cts vs profit 32 cts\n    Net loss 789,300 vs profit 3,953,822\n    Revs 11.7 mln vs 21.1 mln\n    NOTE:  Per share figures reflect five pct stock dividend\npaid December 1986.\n Reuter\n\u0003"
    },
    "PEOPLE": [
        "lyng"
    ],
    "ORGS": [
        "ec"
    ]
}