{
    "DATE": "13-APR-1987 16:04:26.94",
    "TOPICS": [
        "crude"
    ],
    "NEWID": "16651",
    "TEXT": {
        "TITLE": "DOE RESOLVES ISSUES WITH ROYAL DUTCH <RD> UNIT",
        "DATELINE": "    WASHINGTON, April 13 - ",
        "BODY": "The Energy Department said it had\napproved in final form an agreement that resolves all remaining\nissues with Shell Oil Co over oil pricing and allocation\ncontrols that ended in 1981.\n    Under the agreement, The Royal Dutch/Shell Group unit \nagreed to pay 20 mln dlrs to settle refiner pricing issues and\n160 mln dlrs to settle crude oil pricing issues, DOE said.\n    DOE said that before making the pact final, it modified it\nto reflect Shell's compliance with the Tertiary Incentive\nProgram, a provision not in the version published last Dec 31.\n reuter\n\u0003"
    },
    "PLACES": [
        "usa"
    ],
    "PEOPLE": [
        "wilson"
    ],
    "ORGS": [
        "opec"
    ],
    "EXCHENGES": [
        "nasdaq"
    ]
}