{
    "DATE": "19-MAR-1987 07:28:55.45",
    "TOPICS": [
        "money-fx"
    ],
    "PLACES": [
        "japan",
        "usa"
    ],
    "NEWID": "7027",
    "TEXT": {
        "TITLE": "U.K. MONEY MARKET GIVEN 181 MLN STG ASSISTANCE",
        "DATELINE": "    LONDON, March 19 - ",
        "BODY": "The Bank of England said it provided the\nmoney market with 181 mln stg in assistance this morning.\n    This compares with the Bank's revised shortage forecast of\naround 400 mln stg.\n    The central bank purchased bank bills outright at the new\ndealing rates established yesterday.\n    These comprised 65 mln stg in band one at 9-7/8 pct, 114\nmln stg in band two at 9-13/16 pct and two mln stg in band\nthree at 9-3/4 pct.\n REUTER\n\u0003"
    }
}