{
    "DATE": "16-MAR-1987 10:05:06.86",
    "TOPICS": [
        "money-fx"
    ],
    "PLACES": [
        "uk"
    ],
    "NEWID": "5360",
    "TEXT": {
        "TITLE": "U.K. MONEY MARKET GIVEN 550 MLN STG LATE HELP",
        "DATELINE": "    LONDON, March 16 - ",
        "BODY": "The Bank of England said it provided the\nmoney market with late assistance of around 550 mln stg.\n    This takes the Bank's total help today to some 1.12 billion\nstg and compares with its estimated deficit of around 1.10\nbillion.\n REUTER\n\u0003"
    },
    "ORGS": [
        "imf",
        "worldbank"
    ],
    "EXCHENGES": [
        "cbt"
    ],
    "PEOPLE": [
        "hisham-nazer"
    ]
}