{
    "DATE": "18-MAR-1987 17:47:13.46",
    "TOPICS": [
        "crude",
        "nat-gas"
    ],
    "PLACES": [
        "argentina"
    ],
    "NEWID": "6905",
    "TEXT": {
        "TITLE": "ARGENTINE OIL, GAS PRODUCTION FALL IN FEBRUARY",
        "DATELINE": "    BUENOS AIRES, March 18 - ",
        "BODY": "Argentina's total oil and gas\nproduction fell 9.4 pct in February to 2.78 mln cubic metres\nfrom January's total of 3.11 mln cubic metres, the state oil\ncompany Yacimientos Petroliferos Fiscales (YPF) reported.\n    A YPF statement blamed the drop on momentary problems owing\nto the summer season but gave no further details.\n    February's production figure fell slightly short of YPF's\ntarget figure of 2.90 mln cubic metres.\n    Oil production totalled 1.76 mln cubic metres last month\nand natural gas production 1.02 mln cubic metres, down from\n1.95 and 1.15 mln cubic metres in January, respectively.\n Reuter\n\u0003"
    },
    "ORGS": [
        "iwcc"
    ],
    "PEOPLE": [
        "herrington"
    ],
    "EXCHENGES": [
        "lme"
    ]
}