{
    "DATE": "23-MAR-1987 13:42:17.13",
    "TOPICS": [
        "tin"
    ],
    "PLACES": [
        "uk"
    ],
    "NEWID": "8415",
    "TEXT": {
        "TITLE": "TIN PACT SPECIAL SESSION THIS WEEK ROUTINE",
        "DATELINE": "    LONDON, March 23 - ",
        "BODY": "A further special session of the\nInternational Tin Council, ITC, held here tomorrow, March 24,\nwill give member countries an update on the latest debate over\nthe hundreds of millions of sterling lost when its buffer stock\nprice support scheme failed in October 1985, delegates said.\n    But the ITC quarterly session scheduled for April 8-9 will\nbe important, as the council will by then be wanting to decide\non whether the current pact should be extended beyond June 30\nor just allowed to expire, delegates said. A two year extension\nis possible.\n Reuter\n\u0003"
    },
    "EXCHENGES": [
        "cme"
    ],
    "ORGS": [
        "itc"
    ],
    "PEOPLE": [
        "bangemann"
    ]
}