{
    "DATE": " 3-APR-1987 15:36:14.36",
    "TOPICS": [
        "interest"
    ],
    "PLACES": [
        "canada"
    ],
    "NEWID": "13105",
    "TEXT": {
        "TITLE": "BANK OF MONTREAL LOWERS CREDIT CARD RATE",
        "DATELINE": "    TORONTO, April 3 - ",
        "BODY": "Bank of Montreal said it will reduce the\ninterest rate it charges on outstanding MasterCard balances to\n18.3 pct from 21 pct, beginning in July.\n    The bank said it will continue its policy of not charging\nany annual fee or transaction fees to credit card holders.\n                \n Reuter\n\u0003"
    },
    "PEOPLE": [
        "conable"
    ],
    "ORGS": [
        "imf",
        "worldbank"
    ]
}