{
    "DATE": " 3-APR-1987 01:15:32.00",
    "TOPICS": [
        "interest"
    ],
    "PLACES": [
        "new-zealand"
    ],
    "NEWID": "12732",
    "TEXT": {
        "TITLE": "ANZ BANK IN N.Z. RAISES INDICATOR LENDING RATE",
        "DATELINE": "    WELLINGTON, April 3 - ",
        "BODY": "The Australia and New Zealand Banking\nGroup Ltd in New Zealand said it will raise its indicator\nlending rate to 23 pct from 21.5 pct on April 7.\n    A bank statement said the continuing rise in the cost of\nfunds had to be passed on to the lending customers.\n    ANZ managing director Brian Weeks said: \"Recent developments\nin the money markets are of deep concern to all participants\n... Market participants are understandably nervous and cautious\nabout future developments.\n    These include flows to and from the government relating to\nthe privatisation of seven government departments on April 1.\n    \"We welcome the flexibility evident in the Reserve Bank's\nmove to raise the system cash target yesterday, but feel that\nto reduce the present nervousness the cash target and primary\nliquidity level need to be raised further...,\" he said.\n    The Reserve Bank has raised its daily cash target to 45 mln\nN.Z. Dlrs from its normal 30 mln dlrs.\n    Call rates have traded as high as 65 pct this week because\nof business year-end March 31 balance date book squaring.\n    Westpac Banking Corp in New Zealand announced yesterday it\nwould increase its indicator lending rate by 1.5 percentage\npoints to 22.5 pct on April 7.\n REUTER\n\n\n\n\u0003"
    },
    "ORGS": [
        "ico-coffee"
    ],
    "PEOPLE": [
        "yeutter"
    ],
    "EXCHENGES": [
        "nymex"
    ]
}