{
    "DATE": " 9-APR-1987 15:09:06.76",
    "TOPICS": [
        "orange"
    ],
    "PLACES": [
        "usa"
    ],
    "NEWID": "15855",
    "TEXT": {
        "TITLE": "USDA ORANGE JUICE YIELD ESTIMATE",
        "DATELINE": "    WASHINGTON, April 9 - ",
        "BODY": "The U.S. Agriculture Department\nprojected an average yield of 1.50 gallons of frozen\nconcentrated orange juice per box (42.0 degree brix equivalent)\nfrom Florida's 1986/87 crop.\n    That compares with 1.47 gallons per box previously and 1.38\ngallons per box from the 1985/86 crop.\n    The crop reporting board said the estimates for the 1986/87\nseason are based on maturity and yields tests as of April 1.\n Reuter\n\u0003"
    },
    "ORGS": [
        "itc",
        "atpc"
    ],
    "PEOPLE": [
        "balladur"
    ],
    "EXCHENGES": [
        "nyce"
    ]
}