{
    "DATE": "13-MAR-1987 16:43:43.66",
    "TOPICS": [
        "acq"
    ],
    "PLACES": [
        "usa"
    ],
    "NEWID": "5080",
    "TEXT": {
        "TITLE": "TRIBUNE <TRB> COMPLETES CABLE SYSTEM SALE",
        "DATELINE": "    CHICAGO, March 13 - ",
        "BODY": "Tribune Co said it completed the sale\nof the Danville, Va., cable television system to Cablevision\nIndustries Ltd Partnership, affiliated with Cablevision\nIndustries Inc of Liberty, N.Y.\n    It said the Danville system was one of two systems acquired\nby Tribune on September 30, 1986 as part of its purchase of The\nDaily Press Inc, publisher of the Newport News Daily Press and\nThe Times-Herald. Agreements to sell both systems for a total\nof 100 mln dlrs were reached in October.\n    Sale of the Newport News system was completed in December.\n Reuter\n\u0003"
    },
    "ORGS": [
        "ec"
    ],
    "EXCHENGES": [
        "cbt"
    ]
}