{
    "DATE": "12-MAR-1987 07:16:20.36",
    "TOPICS": [
        "earn"
    ],
    "PLACES": [
        "australia"
    ],
    "NEWID": "4120",
    "TEXT": {
        "TITLE": "KIDSTON SAYS HIGHER NET REFLECTS GOLD SALE RISE",
        "DATELINE": "    BRISBANE, March 12 - ",
        "BODY": "<Kidston Gold Mines Ltd> attributed\nthe rise in 1986 net profit to higher prices and an increase in\ngold sales to 237,969 ounces from 206,467 ounces in 1985.\n    The <Placer Development Ltd> offshoot, which operates\nAustralia's largest gold mine, in North Queensland, earlier\nreported net profit rose to 60.50 mln dlrs from 50.76 mln in\nthe 1985 period of 10 months from the start of production.\n    Sales of silver also rose to 165,968 ounces from 109,516.\n    Kidston said in a statement it will spend about 5.5 mln\ndlrs to upgrade its mill grinding circuit to a mill-ball,\nmill-crushing circuit to boost output by 25 pct from end-1987.\n REUTER\n\u0003"
    },
    "PEOPLE": [
        "leigh-pemberton"
    ],
    "ORGS": [
        "ec"
    ]
}