{
    "DATE": " 4-MAR-1987 13:37:10.48",
    "TOPICS": [
        "earn"
    ],
    "PLACES": [
        "usa"
    ],
    "NEWID": "1657",
    "TEXT": {
        "TITLE": "CRI INSURED <CII> TO SET SPECIAL DISTRIBUTION",
        "DATELINE": "    ROCKVILLE, Md., March 4 - ",
        "BODY": "CRI Insured Mortgage Investments\nInc said its advisor will recommend a special distribution of\n50 cts per share due to the sale of a federally insured first\nmortgage on Park Meadows I in Madison, Wis., for 4,267,871\ndlrs.\n    It said it received a 3,695,465 dlr return of capital and\n572,406 dlrs in income on the sale, and the 50 ct distribution\nwould represent a 43.294 ct return of principal and a 6.706 ct\ncapital gain and would be payable June 30 to holders of record\nMay 31.\n Reuter\n\u0003"
    },
    "ORGS": [
        "ec"
    ],
    "EXCHENGES": [
        "amex"
    ]
}